cobra/__init__.py
cobra/__main__.py
cobra/api.py
cobra/api_test.py
cobra/aux_stuff.py
cobra/banner.py
cobra/cli.py
cobra/cli_handler.py
cobra/cli_handler_test.py
cobra/cli_test.py
cobra/conftest.py
cobra/exc.py
cobra/google_drive.py
cobra/hooks.py
cobra/hooks_test.py
cobra_archiver-0.0.5.dist-info/LICENSE
cobra_archiver-0.0.5.dist-info/METADATA
cobra_archiver-0.0.5.dist-info/WHEEL
cobra_archiver-0.0.5.dist-info/entry_points.txt
cobra_archiver-0.0.5.dist-info/top_level.txt
cobra_archiver-0.0.5.dist-info/RECORD
