Metadata-Version: 2.1
Name: cobra-archiver
Version: 0.0.5
Summary: Comprehensive Backing up and Restoration Archiver. Docker volumes, bind mounts and plain directory backup automation tool.
Home-page: https://github.com/yell0w4x/cobra
Author: yell0w4x
Author-email: yell0w4x@gmail.com
License: MIT
Project-URL: Bug Tracker, https://github.com/yell0w4x/cobra/issues
Keywords: Docker volumes backup
Classifier: Programming Language :: Python :: 3
Classifier: Operating System :: OS Independent
Requires-Python: >=3.7
License-File: LICENSE
Requires-Dist: attrs (==22.2.0)
Requires-Dist: cachetools (==5.3.0)
Requires-Dist: certifi (==2022.12.7)
Requires-Dist: charset-normalizer (==3.0.1)
Requires-Dist: docker (==6.0.1)
Requires-Dist: exceptiongroup (==1.1.0)
Requires-Dist: ezenv (==0.92)
Requires-Dist: freezegun (==1.2.2)
Requires-Dist: google-api-core (==2.11.0)
Requires-Dist: google-api-python-client (==2.74.0)
Requires-Dist: google-auth (==2.16.0)
Requires-Dist: google-auth-httplib2 (==0.1.0)
Requires-Dist: google-auth-oauthlib (==0.8.0)
Requires-Dist: googleapis-common-protos (==1.58.0)
Requires-Dist: httplib2 (==0.21.0)
Requires-Dist: idna (==3.4)
Requires-Dist: iniconfig (==2.0.0)
Requires-Dist: markdown-it-py (==2.1.0)
Requires-Dist: mdurl (==0.1.2)
Requires-Dist: oauthlib (==3.2.2)
Requires-Dist: packaging (==23.0)
Requires-Dist: pluggy (==1.0.0)
Requires-Dist: protobuf (==4.21.12)
Requires-Dist: pyasn1 (==0.4.8)
Requires-Dist: pyasn1-modules (==0.2.8)
Requires-Dist: Pygments (==2.14.0)
Requires-Dist: pyparsing (==3.0.9)
Requires-Dist: pyproject-hooks (==1.0.0)
Requires-Dist: pytest (==7.2.1)
Requires-Dist: python-dateutil (==2.8.2)
Requires-Dist: requests (==2.28.2)
Requires-Dist: requests-oauthlib (==1.3.1)
Requires-Dist: rich (==13.3.1)
Requires-Dist: rsa (==4.9)
Requires-Dist: six (==1.16.0)
Requires-Dist: tomli (==2.0.1)
Requires-Dist: uritemplate (==4.1.1)
Requires-Dist: urllib3 (==1.26.14)
Requires-Dist: websocket-client (==1.5.0)
